my_tool.py
app/__init__.py
app/__main__.py
app/application.py
Choicer-0.0.1.dist-info/LICENSE
Choicer-0.0.1.dist-info/METADATA
Choicer-0.0.1.dist-info/WHEEL
Choicer-0.0.1.dist-info/entry_points.txt
Choicer-0.0.1.dist-info/top_level.txt
Choicer-0.0.1.dist-info/RECORD
