Metadata-Version: 2.1
Name: Choicer
Version: 0.0.1
Summary: Helps you make choices.
Home-page: UNKNOWN
Author: Manav Chawla
Author-email: manavachawla@gmail.com
License: MIT
Platform: UNKNOWN
Classifier: Programming Language :: Python :: 3.8
Classifier: Operating System :: OS Independent
Requires-Python: >=3.7
License-File: LICENSE
